target_statistic_encoding/__init__.py
target_statistic_encoding/cat2num.py
target_statistic_encoding/stat_funcs/__init__.py
target_statistic_encoding/stat_funcs/stat_funcs.py
target_statistic_encoding-0.1.4.dist-info/LICENSE
target_statistic_encoding-0.1.4.dist-info/WHEEL
target_statistic_encoding-0.1.4.dist-info/METADATA
target_statistic_encoding-0.1.4.dist-info/RECORD
